setup.py
cryptage/__init__.py
cryptage/encryptor.py
cryptage.egg-info/PKG-INFO
cryptage.egg-info/SOURCES.txt
cryptage.egg-info/dependency_links.txt
cryptage.egg-info/top_level.txt