Metadata-Version: 2.1
Name: cryptage
Version: 0.2
Summary: package pour encryter et decrytper des mots
Home-page: https://github.com/Ferda11/cryptage
Author: Ferda and Mathieu
Author-email: ferdacarinef@gmail.com
Requires-Python: >=3.10
